.gitignore
MANIFEST.in
README.rst
__init__.py
rebuild
setup.py
backstage/__init__.py
backstage/__init__.pyc
backstage/models.py
backstage/models.pyc
backstage/shortcuts.py
backstage/shortcuts.pyc
backstage/version.py
backstage/version.pyc
backstage/act/__init__.py
backstage/act/__init__.pyc
backstage/act/act.py
backstage/act/act.pyc
backstage/act/act_utils.py
backstage/act/act_utils.pyc
backstage/conf/nginx.conf.src
backstage/conf/uwsgi.act.ini.src
backstage/conf/uwsgi.venue.ini.src
backstage/db/README.rst
backstage/db/__init__.py
backstage/db/__init__.pyc
backstage/db/db_tests.py
backstage/db/db_utils.py
backstage/db/db_utils.pyc
backstage/docs/MassiveDjangoHosting.odt
backstage/docs/ModuleModel.ods
backstage/docs/Producer.rst
backstage/producer/README.rst
backstage/producer/__init__.py
backstage/settings/__init__.py
backstage/settings/__init__.pyc
backstage/settings/app_settings.py
backstage/settings/app_settings.pyc
backstage/settings/backstage_settings.py
backstage/settings/backstage_settings.pyc
backstage/settings/cache_settings.py
backstage/settings/db_settings.py
backstage/settings/db_settings.pyc
backstage/settings/django_settings.py
backstage/settings/django_settings.pyc
backstage/settings/fabric_settings.py
backstage/settings/flexipage_settings.py
backstage/settings/flexipage_settings.pyc
backstage/settings/mezzanine_settings.py
backstage/settings/mezzanine_settings.pyc
backstage/settings/misc_settings.py
backstage/settings/misc_settings.pyc
backstage/settings/static_settings.py
backstage/settings/static_settings.pyc
backstage/settings/venue_settings.py
backstage/settings/venue_settings.pyc
backstage/skel/__init__.py
backstage/skel/act/__init__.py
backstage/skel/act/act_apps.py
backstage/skel/act/admin.py
backstage/skel/act/manage.py
backstage/skel/act/urls.py
backstage/skel/act/views.py
backstage/skel/act/wsgi.py
backstage/skel/act/.LIVE/README.rst
backstage/skel/act/cstatic/README.rst
backstage/skel/act/settings/__init__.py
django_backstage.egg-info/PKG-INFO
django_backstage.egg-info/SOURCES.txt
django_backstage.egg-info/dependency_links.txt
django_backstage.egg-info/entry_points.txt
django_backstage.egg-info/requires.txt
django_backstage.egg-info/top_level.txt