Metadata-Version: 1.0
Name: django-backstage
Version: 0.0.423
Summary: Django project and site deployment using virtualenv, uWSGI, nginx, etc.
Home-page: UNKNOWN
Author: MiddleFork
Author-email: walker@mfgis.com
License: UNKNOWN
Platform: UNKNOWN
